graphical.py
__pycache__/graphical.cpython-38.pyc
graphical_formula-0.0.8.dist-info/LICENSE
graphical_formula-0.0.8.dist-info/METADATA
graphical_formula-0.0.8.dist-info/WHEEL
graphical_formula-0.0.8.dist-info/top_level.txt
graphical_formula-0.0.8.dist-info/RECORD
