Metadata-Version: 2.1
Name: graphical-formula
Version: 0.0.8
Summary: 快速的创建和使用图形公式
Home-page: https://github.com/17097231932/graphical/
Author: 17097231932
Author-email: 17097231932@163.com
License: MIT LICENSE
Platform: UNKNOWN
